<annotation>
	<folder>th6</folder>
	<filename>5fe5f34b63aa03044ea4dffd.jpg</filename>
	<path>D:\GitHub\coc_bot\src\base_downloader\layouts\th6\5fe5f34b63aa03044ea4dffd.jpg</path>
	<source>
		<database>Unknown</database>
	</source>
	<size>
		<width>704</width>
		<height>550</height>
		<depth>3</depth>
	</size>
	<segmented>0</segmented>
	<object>
		<name>elixer_collector</name>
		<pose>Unspecified</pose>
		<truncated>0</truncated>
		<difficult>0</difficult>
		<bndbox>
			<xmin>239</xmin>
			<ymin>368</ymin>
			<xmax>295</xmax>
			<ymax>430</ymax>
		</bndbox>
	</object>
	<object>
		<name>elixer_collector</name>
		<pose>Unspecified</pose>
		<truncated>0</truncated>
		<difficult>0</difficult>
		<bndbox>
			<xmin>367</xmin>
			<ymin>401</ymin>
			<xmax>422</xmax>
			<ymax>462</ymax>
		</bndbox>
	</object>
	<object>
		<name>elixer_collector</name>
		<pose>Unspecified</pose>
		<truncated>0</truncated>
		<difficult>0</difficult>
		<bndbox>
			<xmin>408</xmin>
			<ymin>370</ymin>
			<xmax>466</xmax>
			<ymax>428</ymax>
		</bndbox>
	</object>
	<object>
		<name>elixer_collector</name>
		<pose>Unspecified</pose>
		<truncated>0</truncated>
		<difficult>0</difficult>
		<bndbox>
			<xmin>192</xmin>
			<ymin>338</ymin>
			<xmax>252</xmax>
			<ymax>396</ymax>
		</bndbox>
	</object>
	<object>
		<name>elixer_collector</name>
		<pose>Unspecified</pose>
		<truncated>0</truncated>
		<difficult>0</difficult>
		<bndbox>
			<xmin>448</xmin>
			<ymin>332</ymin>
			<xmax>511</xmax>
			<ymax>399</ymax>
		</bndbox>
	</object>
	<object>
		<name>gold_collector</name>
		<pose>Unspecified</pose>
		<truncated>0</truncated>
		<difficult>0</difficult>
		<bndbox>
			<xmin>368</xmin>
			<ymin>54</ymin>
			<xmax>423</xmax>
			<ymax>100</ymax>
		</bndbox>
	</object>
	<object>
		<name>gold_collector</name>
		<pose>Unspecified</pose>
		<truncated>0</truncated>
		<difficult>0</difficult>
		<bndbox>
			<xmin>411</xmin>
			<ymin>86</ymin>
			<xmax>466</xmax>
			<ymax>132</ymax>
		</bndbox>
	</object>
	<object>
		<name>gold_collector</name>
		<pose>Unspecified</pose>
		<truncated>0</truncated>
		<difficult>0</difficult>
		<bndbox>
			<xmin>454</xmin>
			<ymin>119</ymin>
			<xmax>508</xmax>
			<ymax>164</ymax>
		</bndbox>
	</object>
	<object>
		<name>gold_collector</name>
		<pose>Unspecified</pose>
		<truncated>0</truncated>
		<difficult>0</difficult>
		<bndbox>
			<xmin>280</xmin>
			<ymin>53</ymin>
			<xmax>336</xmax>
			<ymax>98</ymax>
		</bndbox>
	</object>
	<object>
		<name>elixer_collector</name>
		<pose>Unspecified</pose>
		<truncated>0</truncated>
		<difficult>0</difficult>
		<bndbox>
			<xmin>282</xmin>
			<ymin>407</ymin>
			<xmax>329</xmax>
			<ymax>462</ymax>
		</bndbox>
	</object>
	<object>
		<name>gold_collector</name>
		<pose>Unspecified</pose>
		<truncated>0</truncated>
		<difficult>0</difficult>
		<bndbox>
			<xmin>235</xmin>
			<ymin>84</ymin>
			<xmax>293</xmax>
			<ymax>133</ymax>
		</bndbox>
	</object>
	<object>
		<name>gold_collector</name>
		<pose>Unspecified</pose>
		<truncated>0</truncated>
		<difficult>0</difficult>
		<bndbox>
			<xmin>195</xmin>
			<ymin>117</ymin>
			<xmax>250</xmax>
			<ymax>165</ymax>
		</bndbox>
	</object>
</annotation>