<annotation>
	<folder>th5</folder>
	<filename>60c20bd134d9ef044a5feade.jpg</filename>
	<path>D:\GitHub\coc_bot\src\base_downloader\layouts\th5\60c20bd134d9ef044a5feade.jpg</path>
	<source>
		<database>Unknown</database>
	</source>
	<size>
		<width>800</width>
		<height>610</height>
		<depth>3</depth>
	</size>
	<segmented>0</segmented>
	<object>
		<name>elixer_collector</name>
		<pose>Unspecified</pose>
		<truncated>0</truncated>
		<difficult>0</difficult>
		<bndbox>
			<xmin>239</xmin>
			<ymin>101</ymin>
			<xmax>306</xmax>
			<ymax>174</ymax>
		</bndbox>
	</object>
	<object>
		<name>gold_collector</name>
		<pose>Unspecified</pose>
		<truncated>0</truncated>
		<difficult>0</difficult>
		<bndbox>
			<xmin>514</xmin>
			<ymin>371</ymin>
			<xmax>589</xmax>
			<ymax>437</ymax>
		</bndbox>
	</object>
	<object>
		<name>elixer_collector</name>
		<pose>Unspecified</pose>
		<truncated>0</truncated>
		<difficult>0</difficult>
		<bndbox>
			<xmin>139</xmin>
			<ymin>172</ymin>
			<xmax>209</xmax>
			<ymax>247</ymax>
		</bndbox>
	</object>
	<object>
		<name>gold_collector</name>
		<pose>Unspecified</pose>
		<truncated>0</truncated>
		<difficult>0</difficult>
		<bndbox>
			<xmin>563</xmin>
			<ymin>334</ymin>
			<xmax>639</xmax>
			<ymax>400</ymax>
		</bndbox>
	</object>
	<object>
		<name>elixer_collector</name>
		<pose>Unspecified</pose>
		<truncated>0</truncated>
		<difficult>0</difficult>
		<bndbox>
			<xmin>363</xmin>
			<ymin>50</ymin>
			<xmax>442</xmax>
			<ymax>127</ymax>
		</bndbox>
	</object>
	<object>
		<name>gold_collector</name>
		<pose>Unspecified</pose>
		<truncated>0</truncated>
		<difficult>0</difficult>
		<bndbox>
			<xmin>611</xmin>
			<ymin>272</ymin>
			<xmax>687</xmax>
			<ymax>340</ymax>
		</bndbox>
	</object>
	<object>
		<name>elixer_collector</name>
		<pose>Unspecified</pose>
		<truncated>0</truncated>
		<difficult>0</difficult>
		<bndbox>
			<xmin>86</xmin>
			<ymin>233</ymin>
			<xmax>157</xmax>
			<ymax>311</ymax>
		</bndbox>
	</object>
	<object>
		<name>gold_collector</name>
		<pose>Unspecified</pose>
		<truncated>0</truncated>
		<difficult>0</difficult>
		<bndbox>
			<xmin>470</xmin>
			<ymin>408</ymin>
			<xmax>541</xmax>
			<ymax>472</ymax>
		</bndbox>
	</object>
	<object>
		<name>gold_collector</name>
		<pose>Unspecified</pose>
		<truncated>0</truncated>
		<difficult>0</difficult>
		<bndbox>
			<xmin>193</xmin>
			<ymin>149</ymin>
			<xmax>255</xmax>
			<ymax>213</ymax>
		</bndbox>
	</object>
	<object>
		<name>elixer_collector</name>
		<pose>Unspecified</pose>
		<truncated>0</truncated>
		<difficult>0</difficult>
		<bndbox>
			<xmin>449</xmin>
			<ymin>86</ymin>
			<xmax>520</xmax>
			<ymax>166</ymax>
		</bndbox>
	</object>
</annotation>
