<annotation>
	<folder>th5</folder>
	<filename>60dd04fd21555e04f2421952.jpg</filename>
	<path>D:\GitHub\coc_bot\src\base_downloader\layouts\th5\60dd04fd21555e04f2421952.jpg</path>
	<source>
		<database>Unknown</database>
	</source>
	<size>
		<width>500</width>
		<height>400</height>
		<depth>3</depth>
	</size>
	<segmented>0</segmented>
	<object>
		<name>gold_collector</name>
		<pose>Unspecified</pose>
		<truncated>0</truncated>
		<difficult>0</difficult>
		<bndbox>
			<xmin>258</xmin>
			<ymin>304</ymin>
			<xmax>291</xmax>
			<ymax>336</ymax>
		</bndbox>
	</object>
	<object>
		<name>gold_collector</name>
		<pose>Unspecified</pose>
		<truncated>0</truncated>
		<difficult>0</difficult>
		<bndbox>
			<xmin>351</xmin>
			<ymin>233</ymin>
			<xmax>389</xmax>
			<ymax>266</ymax>
		</bndbox>
	</object>
	<object>
		<name>gold_collector</name>
		<pose>Unspecified</pose>
		<truncated>0</truncated>
		<difficult>0</difficult>
		<bndbox>
			<xmin>283</xmin>
			<ymin>287</ymin>
			<xmax>316</xmax>
			<ymax>317</ymax>
		</bndbox>
	</object>
	<object>
		<name>gold_collector</name>
		<pose>Unspecified</pose>
		<truncated>0</truncated>
		<difficult>0</difficult>
		<bndbox>
			<xmin>305</xmin>
			<ymin>269</ymin>
			<xmax>341</xmax>
			<ymax>300</ymax>
		</bndbox>
	</object>
	<object>
		<name>gold_collector</name>
		<pose>Unspecified</pose>
		<truncated>0</truncated>
		<difficult>0</difficult>
		<bndbox>
			<xmin>328</xmin>
			<ymin>251</ymin>
			<xmax>364</xmax>
			<ymax>283</ymax>
		</bndbox>
	</object>
	<object>
		<name>elixer_collector</name>
		<pose>Unspecified</pose>
		<truncated>0</truncated>
		<difficult>0</difficult>
		<bndbox>
			<xmin>163</xmin>
			<ymin>261</ymin>
			<xmax>192</xmax>
			<ymax>298</ymax>
		</bndbox>
	</object>
	<object>
		<name>elixer_collector</name>
		<pose>Unspecified</pose>
		<truncated>0</truncated>
		<difficult>0</difficult>
		<bndbox>
			<xmin>140</xmin>
			<ymin>241</ymin>
			<xmax>170</xmax>
			<ymax>282</ymax>
		</bndbox>
	</object>
	<object>
		<name>elixer_collector</name>
		<pose>Unspecified</pose>
		<truncated>0</truncated>
		<difficult>0</difficult>
		<bndbox>
			<xmin>114</xmin>
			<ymin>226</ymin>
			<xmax>148</xmax>
			<ymax>263</ymax>
		</bndbox>
	</object>
	<object>
		<name>elixer_collector</name>
		<pose>Unspecified</pose>
		<truncated>0</truncated>
		<difficult>0</difficult>
		<bndbox>
			<xmin>211</xmin>
			<ymin>299</ymin>
			<xmax>247</xmax>
			<ymax>334</ymax>
		</bndbox>
	</object>
</annotation>
