<annotation>
	<folder>th5</folder>
	<filename>v2-63d3c50d92c8b00515953f9e.jpg</filename>
	<path>D:\GitHub\coc_bot\src\base_downloader\layouts\th5\v2-63d3c50d92c8b00515953f9e.jpg</path>
	<source>
		<database>Unknown</database>
	</source>
	<size>
		<width>1056</width>
		<height>650</height>
		<depth>3</depth>
	</size>
	<segmented>0</segmented>
	<object>
		<name>elixer_collector</name>
		<pose>Unspecified</pose>
		<truncated>0</truncated>
		<difficult>0</difficult>
		<bndbox>
			<xmin>233</xmin>
			<ymin>284</ymin>
			<xmax>296</xmax>
			<ymax>353</ymax>
		</bndbox>
	</object>
	<object>
		<name>gold_collector</name>
		<pose>Unspecified</pose>
		<truncated>0</truncated>
		<difficult>0</difficult>
		<bndbox>
			<xmin>303</xmin>
			<ymin>432</ymin>
			<xmax>380</xmax>
			<ymax>494</ymax>
		</bndbox>
	</object>
	<object>
		<name>gold_collector</name>
		<pose>Unspecified</pose>
		<truncated>0</truncated>
		<difficult>0</difficult>
		<bndbox>
			<xmin>304</xmin>
			<ymin>170</ymin>
			<xmax>374</xmax>
			<ymax>227</ymax>
		</bndbox>
	</object>
	<object>
		<name>elixer_collector</name>
		<pose>Unspecified</pose>
		<truncated>0</truncated>
		<difficult>0</difficult>
		<bndbox>
			<xmin>753</xmin>
			<ymin>232</ymin>
			<xmax>824</xmax>
			<ymax>301</ymax>
		</bndbox>
	</object>
	<object>
		<name>elixer_collector</name>
		<pose>Unspecified</pose>
		<truncated>0</truncated>
		<difficult>0</difficult>
		<bndbox>
			<xmin>387</xmin>
			<ymin>90</ymin>
			<xmax>455</xmax>
			<ymax>159</ymax>
		</bndbox>
	</object>
	<object>
		<name>gold_collector</name>
		<pose>Unspecified</pose>
		<truncated>0</truncated>
		<difficult>0</difficult>
		<bndbox>
			<xmin>560</xmin>
			<ymin>495</ymin>
			<xmax>645</xmax>
			<ymax>558</ymax>
		</bndbox>
	</object>
	<object>
		<name>gold_collector</name>
		<pose>Unspecified</pose>
		<truncated>0</truncated>
		<difficult>0</difficult>
		<bndbox>
			<xmin>562</xmin>
			<ymin>101</ymin>
			<xmax>644</xmax>
			<ymax>163</ymax>
		</bndbox>
	</object>
	<object>
		<name>elixer_collector</name>
		<pose>Unspecified</pose>
		<truncated>0</truncated>
		<difficult>0</difficult>
		<bndbox>
			<xmin>389</xmin>
			<ymin>477</ymin>
			<xmax>456</xmax>
			<ymax>553</ymax>
		</bndbox>
	</object>
	<object>
		<name>elixer_collector</name>
		<pose>Unspecified</pose>
		<truncated>0</truncated>
		<difficult>0</difficult>
		<bndbox>
			<xmin>635</xmin>
			<ymin>431</ymin>
			<xmax>701</xmax>
			<ymax>498</ymax>
		</bndbox>
	</object>
	<object>
		<name>gold_collector</name>
		<pose>Unspecified</pose>
		<truncated>0</truncated>
		<difficult>0</difficult>
		<bndbox>
			<xmin>720</xmin>
			<ymin>301</ymin>
			<xmax>794</xmax>
			<ymax>355</ymax>
		</bndbox>
	</object>
</annotation>
